bbr/__init__.py
bbr-0.0.3.dist-info/DESCRIPTION.rst
bbr-0.0.3.dist-info/METADATA
bbr-0.0.3.dist-info/RECORD
bbr-0.0.3.dist-info/WHEEL
bbr-0.0.3.dist-info/metadata.json
bbr-0.0.3.dist-info/top_level.txt
