Metadata-Version: 2.0
Name: bbr
Version: 0.0.3
Summary: Package to work with URIs from Bebyggelseregistret.
Home-page: https://github.com/Abbe98/bbr-py
Author: Albin Larsson
Author-email: albin.post@gmail.com
License: UNKNOWN
Download-URL: https://github.com/Abbe98/bbr-py/tarball/0.0.3
Keywords: SOCH,K-Samsök,heritage,cultural,BBR
Platform: UNKNOWN
Requires-Dist: ksamsok
Requires-Dist: requests
